ecoindex/backend/VERSION
ecoindex/backend/__init__.py
ecoindex/backend/dependencies/__init__.py
ecoindex/backend/dependencies/bff.py
ecoindex/backend/dependencies/compute.py
ecoindex/backend/dependencies/dates.py
ecoindex/backend/dependencies/host.py
ecoindex/backend/dependencies/id.py
ecoindex/backend/dependencies/pagination.py
ecoindex/backend/dependencies/version.py
ecoindex/backend/main.py
ecoindex/backend/middlewares/cors.py
ecoindex/backend/middlewares/exception_handler.py
ecoindex/backend/models/__init__.py
ecoindex/backend/models/dependencies_parameters/__init__.py
ecoindex/backend/models/dependencies_parameters/bff.py
ecoindex/backend/models/dependencies_parameters/compute.py
ecoindex/backend/models/dependencies_parameters/dates.py
ecoindex/backend/models/dependencies_parameters/host.py
ecoindex/backend/models/dependencies_parameters/id.py
ecoindex/backend/models/dependencies_parameters/pagination.py
ecoindex/backend/models/dependencies_parameters/version.py
ecoindex/backend/models/parameters.py
ecoindex/backend/routers/__init__.py
ecoindex/backend/routers/bff.py
ecoindex/backend/routers/compute.py
ecoindex/backend/routers/ecoindex.py
ecoindex/backend/routers/health.py
ecoindex/backend/routers/host.py
ecoindex/backend/routers/tasks.py
ecoindex/backend/scripts/__init__.py
ecoindex/backend/scripts/openapi.py
ecoindex/backend/services/__init__.py
ecoindex/backend/services/cache.py
ecoindex/backend/services/ecoindex.py
ecoindex/backend/utils/__init__.py
ecoindex/cli/VERSION
ecoindex/cli/__init__.py
ecoindex/cli/app.py
ecoindex/cli/arguments_handler.py
ecoindex/cli/console_output.py
ecoindex/cli/crawl.py
ecoindex/cli/helper.py
ecoindex/cli/report.py
ecoindex/cli/sitemap.py
ecoindex/cli/template.html
ecoindex/worker/__init__.py
ecoindex/worker/health.py
ecoindex/worker/tasks.py
ecoindex/compute/VERSION
ecoindex/compute/__init__.py
ecoindex/compute/ecoindex.py
ecoindex/config/__init__.py
ecoindex/config/settings.py
ecoindex/data/__init__.py
ecobp-0.1.2.dist-info/LICENSE
ecobp-0.1.2.dist-info/METADATA
ecobp-0.1.2.dist-info/WHEEL
ecobp-0.1.2.dist-info/entry_points.txt
ecobp-0.1.2.dist-info/RECORD
