Metadata-Version: 2.1
Name: ecobp
Version: 0.1.2
Summary: 
Author: Vincent Vatelot
Author-email: vincent.vatelot@ik.me
Requires-Python: >=3.10,<3.13
Classifier: Programming Language :: Python :: 3
Classifier: Programming Language :: Python :: 3.10
Classifier: Programming Language :: Python :: 3.11
Classifier: Programming Language :: Python :: 3.12
Requires-Dist: aiofile (>=3.8.8,<4.0.0)
Requires-Dist: loguru (>=0.7.2,<0.8.0)
Requires-Dist: pydantic (>=2.4.2,<3.0.0)
Requires-Dist: pydantic-settings (>=2.0.3,<3.0.0)
Requires-Dist: redis[hiredis] (>=5.0.1,<6.0.0)
Requires-Dist: requests (>=2.31.0,<3.0.0)
Requires-Dist: scrapy (>=2.11.1,<3.0.0)
Requires-Dist: tomli (>=2.0.1,<3.0.0)
